habitica_planner/__init__.py
habitica_planner/planner.py
habitica_planner/i18n/ru/LC_MESSAGES/habitica_planner.mo
habitica_planner-0.1.3.dist-info/DESCRIPTION.rst
habitica_planner-0.1.3.dist-info/METADATA
habitica_planner-0.1.3.dist-info/RECORD
habitica_planner-0.1.3.dist-info/WHEEL
habitica_planner-0.1.3.dist-info/entry_points.txt
habitica_planner-0.1.3.dist-info/metadata.json
habitica_planner-0.1.3.dist-info/top_level.txt
